juicebox_cli/__init__.py
juicebox_cli/auth.py
juicebox_cli/cli.py
juicebox_cli/config.py
juicebox_cli/exceptions.py
juicebox_cli/jb_requests.py
juicebox_cli/logger.py
juicebox_cli/upload.py
juicebox_cli-2.0.0.dist-info/LICENSE.txt
juicebox_cli-2.0.0.dist-info/METADATA
juicebox_cli-2.0.0.dist-info/WHEEL
juicebox_cli-2.0.0.dist-info/entry_points.txt
juicebox_cli-2.0.0.dist-info/top_level.txt
juicebox_cli-2.0.0.dist-info/RECORD
