Metadata-Version: 2.1
Name: juicebox-cli
Version: 2.0.0
Summary: Juicebox CLI
Home-page: https://github.com/juiceinc/juicebox_cli
Author: Juice Analytics
Author-email: tim.oguin@juiceanalytics.com
License: UNKNOWN
Platform: UNKNOWN
Classifier: Development Status :: 4 - Beta
Classifier: Environment :: Console
Classifier: Intended Audience :: End Users/Desktop
Classifier: Intended Audience :: Developers
Classifier: Intended Audience :: System Administrators
Classifier: License :: OSI Approved :: Apache Software License
Classifier: Operating System :: MacOS :: MacOS X
Classifier: Operating System :: Microsoft :: Windows
Classifier: Operating System :: POSIX
Classifier: Programming Language :: Python
Classifier: Programming Language :: Python :: 2
Classifier: Programming Language :: Python :: 2.7
Classifier: Programming Language :: Python :: 3
Classifier: Programming Language :: Python :: 3.4
Classifier: Programming Language :: Python :: 3.5
Classifier: Topic :: Office/Business
Classifier: Topic :: Internet
Classifier: Topic :: Communications :: File Sharing
Requires-Dist: boto3 (==1.7.80)
Requires-Dist: certifi (==2016.8.8)
Requires-Dist: click (==7.0)
Requires-Dist: requests (==2.11.0)
